sonarcloudX/__init__.py
sonarcloudX/abstract.py
sonarcloudX/factories.py
sonarcloudX/project.py
sonarcloudX-0.0.3.dist-info/METADATA
sonarcloudX-0.0.3.dist-info/WHEEL
sonarcloudX-0.0.3.dist-info/top_level.txt
sonarcloudX-0.0.3.dist-info/RECORD
