Metadata-Version: 2.1
Name: sonarcloudX
Version: 0.0.3
Summary: lib para buscar wrapper SonarCloud
Home-page: https://gitlab.com/immigrant-data-driven-development/libs/application/sonarcloud.git
Author: Carlos Henrique Maulaz de Freitas
Author-email: carlosmaulaz@gmail.com
Classifier: Programming Language :: Python :: 3
Classifier: License :: OSI Approved :: MIT License
Classifier: Operating System :: OS Independent
Requires-Dist: python-sonarqube-api
Requires-Dist: factory-boy
